lab07.srcs/sources_1/new/reg_file.v
module RegisterFile (
    input  wire        clk,
    input  wire        rst,
    input  wire        WriteEnable,
    input  wire [4:0]  rs1,
    input  wire [4:0]  rs2,
    input  wire [4:0]  rd,
    input  wire [31:0] WriteData,
    output wire [31:0] ReadData1,
    output wire [31:0] ReadData2
);
    reg [31:0] regs [1:31]; 
    integer i;

    always @(posedge clk) begin
        if (rst) begin
            for (i = 1; i < 32; i = i + 1)
                regs[i] <= 32'b0;
        end else if (WriteEnable && (rd != 5'b0)) begin
            regs[rd] <= WriteData;
        end
    end

    assign ReadData1 = (rs1 == 5'b0) ? 32'b0 : regs[rs1];
    assign ReadData2 = (rs2 == 5'b0) ? 32'b0 : regs[rs2];
endmodule

//`timescale 1ns / 1ps
////////////////////////////////////////////////////////////////////////////////////
//// Company: 
//// Engineer: 
//// 
//// Create Date: 03/05/2026 11:14:24 AM
//// Design Name: 
//// Module Name: reg_file
//// Project Name: 
//// Target Devices: 
//// Tool Versions: 
//// Description: 
//// 
//// Dependencies: 
//// 
//// Revision:
//// Revision 0.01 - File Created
//// Additional Comments:
//// 
////////////////////////////////////////////////////////////////////////////////////


//module RegisterFile (
//    input  wire        clk,
//    input  wire        rst,
//    input  wire        WriteEnable,
//    input  wire [4:0]  rs1,
//    input  wire [4:0]  rs2,
//    input  wire [4:0]  rd,
//    input  wire [31:0] WriteData,
//    output wire [31:0] ReadData1,
//    output wire [31:0] ReadData2
//);

//    // 32 registers, each 32 bits wide
//    reg [31:0] regs [1:31];   // index 0 omitted - x0 is hardwired

//    integer i;

//    // ---- Synchronous write (and reset) ----
//    always @(posedge clk) begin
//        if (rst) begin
//            for (i = 1; i < 32; i = i + 1)
//                regs[i] <= 32'b0;
//        end else if (WriteEnable && (rd != 5'b0)) begin
//            regs[rd] <= WriteData;
//        end
//    end

//    // ---- Asynchronous (combinational) reads ----
//    // x0 is always 0; all other addresses read from the array
//    assign ReadData1 = (rs1 == 5'b0) ? 32'b0 : regs[rs1];
//    assign ReadData2 = (rs2 == 5'b0) ? 32'b0 : regs[rs2];

//endmodule

lab07.srcs/sim_1/new/reg_file_tb.v
`timescale 1ns / 1ps
//////////////////////////////////////////////////////////////////////////////////
// Company: 
// Engineer: 
// 
// Create Date: 03/05/2026 11:16:03 AM
// Design Name: 
// Module Name: reg_file_tb
// Project Name: 
// Target Devices: 
// Tool Versions: 
// Description: 
// 
// Dependencies: 
// 
// Revision:
// Revision 0.01 - File Created
// Additional Comments:
// 
//////////////////////////////////////////////////////////////////////////////////

module RegisterFile_tb;

    // ---- DUT signals ----
    reg         clk, rst, WriteEnable;
    reg  [4:0]  rs1, rs2, rd;
    reg  [31:0] WriteData;
    wire [31:0] ReadData1, ReadData2;

    // ---- Instantiate DUT ----
    RegisterFile dut (
        .clk        (clk),
        .rst        (rst),
        .WriteEnable(WriteEnable),
        .rs1        (rs1),
        .rs2        (rs2),
        .rd         (rd),
        .WriteData  (WriteData),
        .ReadData1  (ReadData1),
        .ReadData2  (ReadData2)
    );

    // ---- Clock: 10 ns period ----
    initial clk = 0;
    always #5 clk = ~clk;

    task check;
        input [127:0] test_name;
        input [31:0]  got, expected;
        begin
            if (got === expected)
                $display("PASS  %s | got=0x%08h", test_name, got);
            else
                $display("FAIL  %s | got=0x%08h expected=0x%08h",
                         test_name, got, expected);
        end
    endtask

    // ---- Stimulus ----
    initial begin
        $dumpfile("RegisterFile_tb.vcd");
        $dumpvars(0, RegisterFile_tb);

        // ---------- Initialise ----------
        rst = 1; WriteEnable = 0;
        rs1 = 0; rs2 = 0; rd = 0; WriteData = 0;
        @(posedge clk); #1;
        rst = 0;

        // ==========================================================
        // TC1 - Write 0xDEADBEEF to x5, then read back on rs1 & rs2
        // ==========================================================
        $display("\n--- TC1: Basic write / read ---");
        WriteEnable = 1;
        rd          = 5'd5;
        WriteData   = 32'hDEADBEEF;
        @(posedge clk); #1;          // latch on this rising edge
        WriteEnable = 0;

        rs1 = 5'd5; rs2 = 5'd0;
        #1;                          // combinational read settles
        check("TC1_rs1", ReadData1, 32'hDEADBEEF);
        check("TC1_rs2_x0", ReadData2, 32'h0);   // rs2=x0 ? always 0

        // ==========================================================
        // TC2 - Attempt to write to x0; x0 must stay 0
        // ==========================================================
        $display("\n--- TC2: Write to x0 (should be ignored) ---");
        WriteEnable = 1;
        rd          = 5'd0;
        WriteData   = 32'hCAFEBABE;
        @(posedge clk); #1;
        WriteEnable = 0;

        rs1 = 5'd0;
        #1;
        check("TC2_x0_unchanged", ReadData1, 32'h0);

        // ==========================================================
        // TC3 - Simultaneous dual-port read (x5 and x5 ? same value)
        //        Also load a second register first
        // ==========================================================
        $display("\n--- TC3: Simultaneous dual-port read ---");
        WriteEnable = 1;
        rd = 5'd7; WriteData = 32'hA5A5A5A5;
        @(posedge clk); #1;
        WriteEnable = 0;

        rs1 = 5'd5; rs2 = 5'd7;   // x5=0xDEADBEEF, x7=0xA5A5A5A5
        #1;
        check("TC3_port1_x5", ReadData1, 32'hDEADBEEF);
        check("TC3_port2_x7", ReadData2, 32'hA5A5A5A5);

        // ==========================================================
        // TC4 - Overwrite x5 and verify old value is replaced
        // ==========================================================
        $display("\n--- TC4: Overwrite register ---");
        WriteEnable = 1;
        rd = 5'd5; WriteData = 32'h12345678;
        @(posedge clk); #1;
        WriteEnable = 0;

        rs1 = 5'd5;
        #1;
        check("TC4_overwrite", ReadData1, 32'h12345678);

        // ==========================================================
        // TC5 - Synchronous reset clears all registers
        // ==========================================================
        $display("\n--- TC5: Synchronous reset ---");
        rst = 1;
        @(posedge clk); #1;
        rst = 0;

        rs1 = 5'd5; rs2 = 5'd7;
        #1;
        check("TC5_x5_after_rst", ReadData1, 32'h0);
        check("TC5_x7_after_rst", ReadData2, 32'h0);

        $display("\n--- Simulation complete ---");
        $finish;
    end

endmodule

lab07.sim/sim_1/behav/xsim/RegisterFile_tb.vcd
$date
   Mon Mar  9 13:50:05 2026
$end
$version
  2020.1
$end
$timescale
  1ps
$end
$scope module RegisterFile_tb $end
$var reg 1 ! clk $end
$var reg 1 " rst $end
$var reg 1 # WriteEnable $end
$var reg 5 $ rs1 [4:0] $end
$var reg 5 % rs2 [4:0] $end
$var reg 5 & rd [4:0] $end
$var reg 32 ' WriteData [31:0] $end
$var wire 32 ( ReadData1 [31:0] $end
$var wire 32 ) ReadData2 [31:0] $end
$scope module dut $end
$var wire 1 * clk $end
$var wire 1 + rst $end
$var wire 1 , WriteEnable $end
$var wire 5 - rs1 [4:0] $end
$var wire 5 . rs2 [4:0] $end
$var wire 5 / rd [4:0] $end
$var wire 32 0 WriteData [31:0] $end
$var wire 32 ( ReadData1 [31:0] $end
$var wire 32 ) ReadData2 [31:0] $end
$var integer 32 1 i $end
$upscope $end
$scope task check $end
$var reg 128 2 test_name [127:0] $end
$var reg 32 3 got [31:0] $end
$var reg 32 4 expected [31:0] $end
$upscope $end
$upscope $end
$enddefinitions $end
#0
$dumpvars
0!
1"
0#
b0 $
b0 %
b0 &
b0 '
b0 (
b0 )
0*
1+
0,
b0 -
b0 .
b0 /
b0 0
bx 1
bx 2
bx 3
bx 4
$end
#5000
1!
1*
#6000
0"
1#
b101 &
b11011110101011011011111011101111 '
0+
1,
b101 /
b11011110101011011011111011101111 0
#10000
0!
0*
#15000
1!
1*
#16000
0#
b101 $
b0 %
b11011110101011011011111011101111 (
0,
b101 -
#17000
1#
b0 &
b11001010111111101011101010111110 '
1,
b0 /
b11001010111111101011101010111110 0
b1010100010000110011000101011111011100100111001100110010010111110111100000110000 2
b0 3
b0 4
#20000
0!
0*
#25000
1!
1*
#26000
0#
b0 $
b0 (
0,
b0 -
#27000
1#
b111 &
b10100101101001011010010110100101 '
1,
b111 /
b10100101101001011010010110100101 0
b1010100010000110011001001011111011110000011000001011111011101010110111001100011011010000110000101101110011001110110010101100100 2
#30000
0!
0*
#35000
1!
1*
#36000
0#
b101 $
b111 %
b11011110101011011011111011101111 (
b10100101101001011010010110100101 )
0,
b101 -
b111 .
#37000
1#
b101 &
b10010001101000101011001111000 '
1,
b101 /
b10010001101000101011001111000 0
b10101000100001100110011010111110111000001101111011100100111010000110010010111110111100000110111 2
b10100101101001011010010110100101 3
b10100101101001011010010110100101 4
#40000
0!
0*
#45000
1!
b10010001101000101011001111000 (
1*
#46000
0#
b101 $
0,
#47000
1"
1+
b1010100010000110011010001011111011011110111011001100101011100100111011101110010011010010111010001100101 2
b10010001101000101011001111000 3
b10010001101000101011001111000 4
#50000
0!
0*
#55000
1!
b0 (
b0 )
1*
#56000
0"
b101 $
b111 %
0+
#57000
b1010100010000110011010101011111011110000011011101011111011000010110011001110100011001010111001001011111011100100111001101110100 2
b0 3
b0 4
